{
  "resourceType": "ConceptMap",
  "id": "A-2-OrderInformationMapping",
  "url": "http://hl7.eu/fhir/imaging/ConceptMap/A-2-OrderInformationMapping",
  "title": "A.2 Order Information to FHIR profiles",
  "group": [
    {
      "element": [
        {
          "target": [
            {
              "code": "requester",
              "display": "",
              "relationship": "equivalent"
            }
          ],
          "code": "requester",
          "display": "A.2 Order Placer"
        },
        {
          "target": [
            {
              "code": "identifier[accession-number]",
              "display": "",
              "relationship": "equivalent"
            }
          ],
          "code": "orderId",
          "display": "A.2.1 Order ID"
        },
        {
          "target": [
            {
              "code": "identifier[order-id]",
              "display": "",
              "relationship": "equivalent"
            }
          ],
          "code": "orderId",
          "display": "A.2.1 Order ID"
        },
        {
          "target": [
            {
              "code": "authoredOn",
              "display": "",
              "relationship": "equivalent"
            }
          ],
          "code": "orderDateTime",
          "display": "A.2.2 Order date and time"
        },
        {
          "target": [
            {
              "code": "practitioner.practitioner.identifier",
              "display": "",
              "relationship": "equivalent"
            }
          ],
          "code": "orderPlacerIdentifier",
          "display": "A.2.3 Order placer professional identifier"
        },
        {
          "target": [
            {
              "code": "practitioner.practitioner.name",
              "display": "",
              "relationship": "equivalent"
            }
          ],
          "code": "orderPlacerName",
          "display": "A.2.4 Order placer name"
        },
        {
          "target": [
            {
              "code": "practitioner.practitioner.name",
              "display": "",
              "relationship": "equivalent"
            }
          ],
          "code": "orderPlacerSpecialty",
          "display": "A.2.5 Order placer specialty"
        },
        {
          "target": [
            {
              "code": "practitioner.practitioner.address",
              "display": "",
              "relationship": "source-is-broader-than-target"
            }
          ],
          "code": "orderPlacerContactDetails",
          "display": "A.2.6 Order placer contact details"
        },
        {
          "target": [
            {
              "code": "practitioner.practitioner.telecom",
              "display": "",
              "relationship": "source-is-broader-than-target"
            }
          ],
          "code": "orderPlacerContactDetails",
          "display": "A.2.6 Order placer contact details"
        },
        {
          "target": [
            {
              "code": "practitioner.organization",
              "display": "",
              "relationship": "equivalent"
            }
          ],
          "code": "orderPlacerOrganization",
          "display": "A.2.7 Order placer organization"
        }
      ],
      "source": "http://hl7.eu/fhir/imaging/StructureDefinition/ehn-medical-imaging-report-order",
      "target": "http://hl7.eu/fhir/imaging/StructureDefinition/im-order"
    },
    {
      "element": [
        {
          "target": [
            {
              "code": "practitioner.identifier",
              "display": "",
              "relationship": "equivalent"
            }
          ],
          "code": "orderPlacerIdentifier",
          "display": "A.2.3 Order placer professional identifier"
        },
        {
          "target": [
            {
              "code": "practitioner.name",
              "display": "",
              "relationship": "equivalent"
            }
          ],
          "code": "orderPlacerName",
          "display": "A.2.4 Order placer name"
        },
        {
          "target": [
            {
              "code": "specialty",
              "display": "",
              "relationship": "equivalent"
            }
          ],
          "code": "orderPlacerSpecialty",
          "display": "A.2.5 Order placer specialty"
        },
        {
          "target": [
            {
              "code": "practitioner.address",
              "display": "",
              "relationship": "source-is-broader-than-target"
            }
          ],
          "code": "orderPlacerContactDetails",
          "display": "A.2.6 Order placer contact details"
        },
        {
          "target": [
            {
              "code": "practitioner.telecom",
              "display": "",
              "relationship": "source-is-broader-than-target"
            }
          ],
          "code": "orderPlacerContactDetails",
          "display": "A.2.6 Order placer contact details"
        },
        {
          "target": [
            {
              "code": "organization",
              "display": "",
              "relationship": "equivalent"
            }
          ],
          "code": "orderPlacerOrganization",
          "display": "A.2.7 Order placer organization"
        }
      ],
      "source": "http://hl7.eu/fhir/imaging/StructureDefinition/ehn-medical-imaging-report-order",
      "target": "http://hl7.eu/fhir/imaging/StructureDefinition/im-order-placer"
    },
    {
      "element": [
        {
          "target": [
            {
              "code": "identifier",
              "display": "",
              "relationship": "equivalent"
            }
          ],
          "code": "orderPlacerIdentifier",
          "display": "A.2.3 Order placer professional identifier"
        },
        {
          "target": [
            {
              "code": "name",
              "display": "",
              "relationship": "equivalent"
            }
          ],
          "code": "orderPlacerName",
          "display": "A.2.4 Order placer name"
        },
        {
          "target": [
            {
              "code": "address",
              "display": "",
              "relationship": "source-is-broader-than-target"
            }
          ],
          "code": "orderPlacerContactDetails",
          "display": "A.2.6 Order placer contact details"
        },
        {
          "target": [
            {
              "code": "telecom",
              "display": "",
              "relationship": "source-is-broader-than-target"
            }
          ],
          "code": "orderPlacerContactDetails",
          "display": "A.2.6 Order placer contact details"
        }
      ],
      "source": "http://hl7.eu/fhir/imaging/StructureDefinition/ehn-medical-imaging-report-order",
      "target": "http://hl7.eu/fhir/imaging/StructureDefinition/im-practitioner"
    },
    {
      "element": [
        {
          "target": [
            {
              "code": "name",
              "display": "",
              "relationship": "equivalent"
            }
          ],
          "code": "orderPlacerOrganization",
          "display": "A.2.7 Order placer organization"
        }
      ],
      "source": "http://hl7.eu/fhir/imaging/StructureDefinition/ehn-medical-imaging-report-order",
      "target": "http://hl7.eu/fhir/imaging/StructureDefinition/im-organization"
    },
    {
      "element": [
        {
          "target": [
            {
              "code": "name",
              "display": "",
              "relationship": "equivalent"
            }
          ],
          "code": "orderPlacerOrganization",
          "display": "A.2.7 Order placer organization"
        }
      ],
      "source": "http://hl7.eu/fhir/imaging/StructureDefinition/ehn-medical-imaging-report-order",
      "target": "http://hl7.eu/fhir/imaging/StructureDefinition/im-composition"
    },
    {
      "element": [
        {
          "target": [
            {
              "code": "based[ImOrder]",
              "display": "",
              "relationship": "equivalent"
            }
          ],
          "code": "orderInformation",
          "display": "A.2 Order Information"
        }
      ],
      "source": "http://hl7.eu/fhir/imaging/StructureDefinition/ehn-medical-imaging-report",
      "target": "http://hl7.eu/fhir/imaging/StructureDefinition/im-composition"
    },
    {
      "element": [
        {
          "target": [
            {
              "code": "based[ImOrder]",
              "display": "",
              "relationship": "equivalent"
            }
          ],
          "code": "orderInformation",
          "display": "A.2 Order Information"
        }
      ],
      "source": "http://hl7.eu/fhir/imaging/StructureDefinition/ehn-medical-imaging-report",
      "target": "http://hl7.eu/fhir/imaging/StructureDefinition/im-diagnostic-report"
    }
  ],
  "name": "A.2",
  "status": "draft",
  "experimental": true,
  "description": "This concept map defines the mapping between the A.2 Order Information section and the FHIR profiles.",
  "sourceScopeUri": "http://hl7.eu/fhir/imaging/StructureDefinition/ehn-medical-imaging-report-order"
}
